{
  "timestamp": "2025-08-08 08:29:52",
  "agent": "AGENT1",
  "key": "AP",
  "type": "OUTPUT",
  "output": {
    "content": {
      "content": "The accounts payable balance as at 30 September 2022 mainly entailed management consulting fees to Business Management Consulting Co. of CNY2.3M and logistics services fees to Logistics Development Co., Ltd. of CNY8.3M.\n\nSUMMARY: Used entities 'Business Management Consulting Co.' (CNY2.3M) and 'Logistics Development Co., Ltd.' (CNY8.3M), which constitute the majority of the total CNY11.8M accounts payable balance.",
      "pattern_used": "Pattern 1",
      "table_data": [
        {
          "sheet": "AP",
          "data": "    Unnamed: 0                        Unnamed: 1           Unnamed: 2\n27         NaN  Accounts payable - Haining Wanpu                  NaN\n28         NaN                               NaN  Indicative adjusted\n29         NaN                           CNY'000  2022-09-30 00:00:00\n30         NaN                  Project payables                  NaN\n31         NaN                        Company #1                    0\n32         NaN                        Company #2                    0\n33         NaN                        Company #3                    0\n34         NaN                        Company #4                    0\n35         NaN                        Company #5                    0\n36         NaN                        Company #6                    0\n37         NaN                        Company #7                    0\n38         NaN                        Company #8                    0\n39         NaN         Project payables subtotal                    0\n40         NaN                  Accrued expenses                  NaN\n41         NaN                        Company #1                    0\n42         NaN                        Company #2                    0\n43         NaN                            進項稅金中轉                    0\n44         NaN                           自來水有限公司                    0\n45         NaN                        仲量聯行北京諮詢公司                   13\n46         NaN                信用中和會計師事務所(特殊普通合夥)                   14\n47         NaN                       進項稅(已認證未入帳)                    0\n48         NaN                          企業管理諮詢公司                 2295\n49         NaN         Accrued expenses subtotal                   27\n50         NaN            Related party payables                  NaN\n51         NaN                      科技有限公司(戰區運營)                   19\n52         NaN                          物業服務有限公司                 1149\n53         NaN                          物流發展有限公司                 8313\n54         NaN   Related party payables Subtotal                 9481\n55         NaN                             Total                11776",
          "parsed_data": {
            "metadata": {
              "table_name": "AP - Haining",
              "sheet_name": "AP",
              "date": "2022-09-30",
              "currency_info": "CNY'000",
              "multiplier": 1000,
              "value_column": "Indicative adjusted",
              "data_start_row": 2
            },
            "data": [
              {
                "description": "Project payables",
                "value": 0,
                "original_value": "nan",
                "is_total": false
              },
              {
                "description": "Company #1",
                "value": 0.0,
                "original_value": "0",
                "is_total": false
              },
              {
                "description": "Company #2",
                "value": 0.0,
                "original_value": "0",
                "is_total": false
              },
              {
                "description": "Company #3",
                "value": 0.0,
                "original_value": "0",
                "is_total": false
              },
              {
                "description": "Company #4",
                "value": 0.0,
                "original_value": "0",
                "is_total": false
              },
              {
                "description": "Company #5",
                "value": 0.0,
                "original_value": "0",
                "is_total": false
              },
              {
                "description": "Company #6",
                "value": 0.0,
                "original_value": "0",
                "is_total": false
              },
              {
                "description": "Company #7",
                "value": 0.0,
                "original_value": "0",
                "is_total": false
              },
              {
                "description": "Company #8",
                "value": 0.0,
                "original_value": "0",
                "is_total": false
              },
              {
                "description": "Project payables subtotal",
                "value": 0.0,
                "original_value": "0",
                "is_total": false
              },
              {
                "description": "Accrued expenses",
                "value": 0,
                "original_value": "nan",
                "is_total": false
              },
              {
                "description": "Company #1",
                "value": 0.0,
                "original_value": "0",
                "is_total": false
              },
              {
                "description": "Company #2",
                "value": 0.0,
                "original_value": "0",
                "is_total": false
              },
              {
                "description": "進項稅金中轉",
                "value": 0.0,
                "original_value": "0",
                "is_total": false
              },
              {
                "description": "自來水有限公司",
                "value": 0.0,
                "original_value": "0",
                "is_total": false
              },
              {
                "description": "仲量聯行北京諮詢公司",
                "value": 13000.0,
                "original_value": "13",
                "is_total": false
              },
              {
                "description": "信用中和會計師事務所(特殊普通合夥)",
                "value": 14000.0,
                "original_value": "14",
                "is_total": false
              },
              {
                "description": "進項稅(已認證未入帳)",
                "value": 0.0,
                "original_value": "0",
                "is_total": false
              },
              {
                "description": "企業管理諮詢公司",
                "value": 2295000.0,
                "original_value": "2295",
                "is_total": false
              },
              {
                "description": "Accrued expenses subtotal",
                "value": 27000.0,
                "original_value": "27",
                "is_total": false
              },
              {
                "description": "Related party payables",
                "value": 0,
                "original_value": "nan",
                "is_total": false
              },
              {
                "description": "科技有限公司(戰區運營)",
                "value": 19000.0,
                "original_value": "19",
                "is_total": false
              },
              {
                "description": "物業服務有限公司",
                "value": 1149000.0,
                "original_value": "1149",
                "is_total": false
              },
              {
                "description": "物流發展有限公司",
                "value": 8313000.0,
                "original_value": "8313",
                "is_total": false
              },
              {
                "description": "Related party payables Subtotal",
                "value": 9481000.0,
                "original_value": "9481",
                "is_total": false
              },
              {
                "description": "Total",
                "value": 11776000.0,
                "original_value": "11776",
                "is_total": true
              }
            ],
            "raw_df": "                          Unnamed: 1           Unnamed: 2\n27  Accounts payable - Haining Wanpu                  NaN\n28                               NaN  Indicative adjusted\n29                           CNY'000  2022-09-30 00:00:00\n30                  Project payables                  NaN\n31                        Company #1                    0\n32                        Company #2                    0\n33                        Company #3                    0\n34                        Company #4                    0\n35                        Company #5                    0\n36                        Company #6                    0\n37                        Company #7                    0\n38                        Company #8                    0\n39         Project payables subtotal                    0\n40                  Accrued expenses                  NaN\n41                        Company #1                    0\n42                        Company #2                    0\n43                            進項稅金中轉                    0\n44                           自來水有限公司                    0\n45                        仲量聯行北京諮詢公司                   13\n46                信用中和會計師事務所(特殊普通合夥)                   14\n47                       進項稅(已認證未入帳)                    0\n48                          企業管理諮詢公司                 2295\n49         Accrued expenses subtotal                   27\n50            Related party payables                  NaN\n51                      科技有限公司(戰區運營)                   19\n52                          物業服務有限公司                 1149\n53                          物流發展有限公司                 8313\n54   Related party payables Subtotal                 9481\n55                             Total                11776"
          },
          "markdown": "**AP - Haining**\n*Sheet: AP*\n*Date: 30-Sep-2022*\n*Currency: CNY'000*\n*Value Column: Indicative adjusted*\n\n| Description | Value |\n|-------------|--------|\n| Project payables | 0.00 |\n| Company #1 | 0.00 |\n| Company #2 | 0.00 |\n| Company #3 | 0.00 |\n| Company #4 | 0.00 |\n| Company #5 | 0.00 |\n| Company #6 | 0.00 |\n| Company #7 | 0.00 |\n| Company #8 | 0.00 |\n| Project payables subtotal | 0.00 |\n| Accrued expenses | 0.00 |\n| Company #1 | 0.00 |\n| Company #2 | 0.00 |\n| 進項稅金中轉 | 0.00 |\n| 自來水有限公司 | 0.00 |\n| 仲量聯行北京諮詢公司 | 13,000.00 |\n| 信用中和會計師事務所(特殊普通合夥) | 14,000.00 |\n| 進項稅(已認證未入帳) | 0.00 |\n| 企業管理諮詢公司 | 2,295,000.00 |\n| Accrued expenses subtotal | 27,000.00 |\n| Related party payables | 0.00 |\n| 科技有限公司(戰區運營) | 19,000.00 |\n| 物業服務有限公司 | 1,149,000.00 |\n| 物流發展有限公司 | 8,313,000.00 |\n| Related party payables Subtotal | 9,481,000.00 |\n| **Total** | **11,776,000.00** |",
          "entity_match": "True"
        }
      ],
      "financial_figure": 11776000.0,
      "entity_name": "Haining"
    },
    "length": 7965,
    "format": "json"
  },
  "processing": {
    "time_seconds": 8.95069522327847,
    "status": "success",
    "is_success": true
  },
  "session_id": "20250808_082826"
}